biomappings/.DS_Store
biomappings/__init__.py
biomappings/__main__.py
biomappings/apicuron.py
biomappings/cli.py
biomappings/contribute/__init__.py
biomappings/contribute/obo.py
biomappings/contribute/utils.py
biomappings/graph.py
biomappings/lexical.py
biomappings/mapping_graph.py
biomappings/paper_analysis.py
biomappings/py.typed
biomappings/resources/.DS_Store
biomappings/resources/__init__.py
biomappings/resources/curators.tsv
biomappings/resources/export_sssom.py
biomappings/resources/negative.sssom.tsv
biomappings/resources/positive.sssom.tsv
biomappings/resources/predictions.sssom.tsv
biomappings/resources/semapv.json
biomappings/resources/semapv.py
biomappings/resources/unsure.sssom.tsv
biomappings/resources/update_curated.py
biomappings/summary.py
biomappings/templates/base.html
biomappings/templates/home.html
biomappings/templates/summary.html
biomappings/testing.py
biomappings/upload_ndex.py
biomappings/utils.py
biomappings/wsgi.py
biomappings-0.4.2.dist-info/licenses/LICENSE
biomappings-0.4.2.dist-info/WHEEL
biomappings-0.4.2.dist-info/entry_points.txt
biomappings-0.4.2.dist-info/METADATA
biomappings-0.4.2.dist-info/RECORD
