Metadata-Version: 2.4
Name: biomappings
Version: 0.4.2
Summary: Curated and predicted mappings between biomedical identifiers in different namespaces
Keywords: snekpack,cookiecutter,biology,chemistry,ontologies,ontology,nlp
Author: Charles Tapley Hoyt
Author-email: Charles Tapley Hoyt <cthoyt@gmail.com>
License-File: LICENSE
Classifier: Development Status :: 4 - Beta
Classifier: Environment :: Console
Classifier: Intended Audience :: Science/Research
Classifier: License :: OSI Approved :: MIT License
Classifier: Operating System :: OS Independent
Classifier: Framework :: Pytest
Classifier: Framework :: tox
Classifier: Framework :: Sphinx
Classifier: Natural Language :: English
Classifier: Programming Language :: Python
Classifier: Programming Language :: Python :: 3.9
Classifier: Programming Language :: Python :: 3.10
Classifier: Programming Language :: Python :: 3.11
Classifier: Programming Language :: Python :: 3.12
Classifier: Programming Language :: Python :: 3.13
Classifier: Programming Language :: Python :: 3 :: Only
Classifier: Typing :: Typed
Classifier: Topic :: Scientific/Engineering :: Chemistry
Classifier: Topic :: Scientific/Engineering :: Bio-Informatics
Requires-Dist: networkx
Requires-Dist: requests
Requires-Dist: click
Requires-Dist: pyyaml
Requires-Dist: tqdm
Requires-Dist: pystow>=0.2.7
Requires-Dist: bioregistry>=0.10.43
Requires-Dist: apicuron-client ; extra == 'apicuron'
Requires-Dist: matplotlib ; extra == 'charts'
Requires-Dist: seaborn ; extra == 'charts'
Requires-Dist: sphinx>=8 ; extra == 'docs'
Requires-Dist: sphinx-rtd-theme>=3.0 ; extra == 'docs'
Requires-Dist: sphinx-click ; extra == 'docs'
Requires-Dist: sphinx-automodapi ; extra == 'docs'
Requires-Dist: sentence-transformers ; extra == 'embedding'
Requires-Dist: torch ; extra == 'embedding'
Requires-Dist: sssom ; extra == 'exports'
Requires-Dist: pandas ; extra == 'exports'
Requires-Dist: pyobo[gilda]>=0.12.0 ; extra == 'gilda'
Requires-Dist: pyobo[gilda-slim]>=0.12.0 ; extra == 'gilda-slim'
Requires-Dist: ndex2 ; extra == 'ndex'
Requires-Dist: pyobo>=0.12.8 ; extra == 'pyobo'
Requires-Dist: pytest ; extra == 'tests'
Requires-Dist: coverage[toml] ; extra == 'tests'
Requires-Dist: flask ; extra == 'web'
Requires-Dist: bootstrap-flask ; extra == 'web'
Requires-Dist: flask-wtf ; extra == 'web'
Maintainer: Charles Tapley Hoyt
Maintainer-email: Charles Tapley Hoyt <cthoyt@gmail.com>
Requires-Python: >=3.9
Project-URL: Bug Tracker, https://github.com/biopragmatics/biomappings/issues
Project-URL: Documentation, https://biomappings.readthedocs.io
Project-URL: Funding, https://github.com/sponsors/
Project-URL: Homepage, https://github.com/biopragmatics/biomappings
Project-URL: Repository, https://github.com/biopragmatics/biomappings.git
Provides-Extra: apicuron
Provides-Extra: charts
Provides-Extra: docs
Provides-Extra: embedding
Provides-Extra: exports
Provides-Extra: gilda
Provides-Extra: gilda-slim
Provides-Extra: ndex
Provides-Extra: pyobo
Provides-Extra: tests
Provides-Extra: web
